setup.py
funniest_5g/__init__.py
funniest_5g.egg-info/PKG-INFO
funniest_5g.egg-info/SOURCES.txt
funniest_5g.egg-info/dependency_links.txt
funniest_5g.egg-info/not-zip-safe
funniest_5g.egg-info/top_level.txt