Metadata-Version: 1.0
Name: funniest-5g
Version: 1.0
Summary: The funniest joke in the world
Home-page: http://github.com/storborg/funniest
Author: Cathy
Author-email: cathy.mao@nokia-sbell.com
License: MIT
Platform: UNKNOWN
